dostlang/__init__.py
dostlang/dostlang.py
dostlang-1.0.0.dist-info/LICENSE
dostlang-1.0.0.dist-info/METADATA
dostlang-1.0.0.dist-info/WHEEL
dostlang-1.0.0.dist-info/top_level.txt
dostlang-1.0.0.dist-info/RECORD
