Metadata-Version: 2.1
Name: dostlang
Version: 1.0.0
Summary: This package is used for making python funny
Home-page: https://github.com/UjjwalxD/dostlang-module
Author: Ujjwal Srivastav
Author-email: ujjwalfixa@gmail.com
Project-URL: Bug Tracker, https://github.com/UjjwalxD/dostlang-module/issues
Classifier: Programming Language :: Python :: 3
Classifier: License :: OSI Approved :: MIT License
Classifier: Operating System :: OS Independent
Requires-Python: >=3.6
License-File: LICENSE
